databricks_claude/__about__.py
databricks_claude/__init__.py
databricks_claude/cli.py
databricks_claude/core.py
databricks_claude/exceptions.py
databricks_claude-0.0.2.dist-info/METADATA
databricks_claude-0.0.2.dist-info/WHEEL
databricks_claude-0.0.2.dist-info/entry_points.txt
databricks_claude-0.0.2.dist-info/licenses/LICENSE
databricks_claude-0.0.2.dist-info/RECORD
